scam/CLI.py
scam/CommManager.py
scam/__init__.py
scam_me-0.2.1.data/scripts/scam_me
scam_me-0.2.1.dist-info/LICENSE
scam_me-0.2.1.dist-info/METADATA
scam_me-0.2.1.dist-info/WHEEL
scam_me-0.2.1.dist-info/top_level.txt
scam_me-0.2.1.dist-info/RECORD
