Metadata-Version: 2.1
Name: scam-me
Version: 0.2.1
Summary: SCAM Main Edition: Simple Crud Arrangement Manager
Home-page: UNKNOWN
Author: Mario Marino
Author-email: m.marino35@campus.unimib.it
License: UNKNOWN
Platform: UNKNOWN
Requires-Dist: requests
